rootly_mcp_server/__init__.py
rootly_mcp_server/__main__.py
rootly_mcp_server/client.py
rootly_mcp_server/exceptions.py
rootly_mcp_server/monitoring.py
rootly_mcp_server/pagination.py
rootly_mcp_server/security.py
rootly_mcp_server/server.py
rootly_mcp_server/smart_utils.py
rootly_mcp_server/texttest.json
rootly_mcp_server/utils.py
rootly_mcp_server/validators.py
rootly_mcp_server/data/__init__.py
rootly_mcp_server-2.1.0.dist-info/METADATA
rootly_mcp_server-2.1.0.dist-info/WHEEL
rootly_mcp_server-2.1.0.dist-info/entry_points.txt
rootly_mcp_server-2.1.0.dist-info/licenses/LICENSE
rootly_mcp_server-2.1.0.dist-info/RECORD
