Metadata-Version: 2.4
Name: rootly-mcp-server
Version: 2.1.0
Summary: Secure Model Context Protocol server for Rootly APIs with AI SRE capabilities, comprehensive error handling, and input validation
Project-URL: Homepage, https://github.com/Rootly-AI-Labs/Rootly-MCP-server
Project-URL: Issues, https://github.com/Rootly-AI-Labs/Rootly-MCP-server/issues
Author-email: Rootly AI Labs <support@rootly.com>
License-Expression: Apache-2.0
License-File: LICENSE
Keywords: ai-sre,automation,devops,incident-management,incidents,llm,mcp,on-call,rate-limiting,rootly,security,sre
Classifier: Development Status :: 5 - Production/Stable
Classifier: Intended Audience :: Developers
Classifier: Intended Audience :: System Administrators
Classifier: License :: OSI Approved :: Apache Software License
Classifier: Operating System :: OS Independent
Classifier: Programming Language :: Python :: 3
Classifier: Programming Language :: Python :: 3.10
Classifier: Programming Language :: Python :: 3.11
Classifier: Programming Language :: Python :: 3.12
Classifier: Topic :: Security
Classifier: Topic :: Software Development :: Build Tools
Classifier: Topic :: System :: Monitoring
Classifier: Topic :: System :: Systems Administration
Requires-Python: >=3.10
Requires-Dist: brotli>=1.0.0
Requires-Dist: fastmcp>=2.9.0
Requires-Dist: httpx>=0.24.0
Requires-Dist: numpy>=1.24.0
Requires-Dist: pydantic>=2.0.0
Requires-Dist: requests>=2.28.0
Requires-Dist: scikit-learn>=1.3.0
Provides-Extra: dev
Requires-Dist: bandit>=1.7.0; extra == 'dev'
Requires-Dist: black>=23.0.0; extra == 'dev'
Requires-Dist: isort>=5.0.0; extra == 'dev'
Requires-Dist: mypy>=1.0.0; extra == 'dev'
Requires-Dist: safety>=2.0.0; extra == 'dev'
